hermitage_alchemy/__init__.py
hermitage_alchemy/assembling.py
hermitage_alchemy/bootstraping.py
hermitage_alchemy/configuration.py
hermitage_alchemy/definition/__init__.py
hermitage_alchemy/definition/contracts.py
hermitage_alchemy/execution/__init__.py
hermitage_alchemy/execution/read.py
hermitage_alchemy/execution/write.py
hermitage_alchemy/types/__init__.py
hermitage_alchemy/types/jsonb/__init__.py
hermitage_alchemy/types/jsonb/decoding.py
hermitage_alchemy/types/jsonb/encoding.py
hermitage_alchemy-0.3.7.dist-info/METADATA
hermitage_alchemy-0.3.7.dist-info/WHEEL
hermitage_alchemy-0.3.7.dist-info/RECORD
