Metadata-Version: 2.1
Name: hermitage-alchemy
Version: 0.3.7
Summary: Implementation of hermitage contracts for sqlalchemy engine
Author: Smairon
Author-email: man@smairon.ru
Requires-Python: >=3.11,<4.0
Classifier: Programming Language :: Python :: 3
Classifier: Programming Language :: Python :: 3.11
Classifier: Programming Language :: Python :: 3.12
Requires-Dist: hermitage (>=0.3.0,<0.4.0)
Requires-Dist: sqlalchemy (>=2.0.20,<3.0.0)
